EbookTranslator/All_Translation.py
EbookTranslator/Deepl_Translation.py
EbookTranslator/LLMS_translation.py
EbookTranslator/YouDao_translation.py
EbookTranslator/__init__.py
EbookTranslator/cli.py
EbookTranslator/convert2pdf.py
EbookTranslator/load_config.py
EbookTranslator/main_function.py
EbookTranslator-0.3.3.dist-info/LICENSE
EbookTranslator-0.3.3.dist-info/METADATA
EbookTranslator-0.3.3.dist-info/WHEEL
EbookTranslator-0.3.3.dist-info/entry_points.txt
EbookTranslator-0.3.3.dist-info/top_level.txt
EbookTranslator-0.3.3.dist-info/RECORD
