Metadata-Version: 2.1
Name: EbookTranslator
Version: 0.3.3
Summary: The world's highest performing e-book retention layout translation library
Home-page: https://github.com/1421243966/EbookTranslator
Author: Chen
Author-email: 1421243966@qq.com
License: UNKNOWN
Project-URL: Bug Reports, https://github.com/1421243966/EbookTranslator/issues
Project-URL: Source, https://github.com/1421243966/EbookTranslator
Project-URL: Documentation, https://github.com/1421243966/EbookTranslator#readme
Keywords: ebook,translation,pdf,ocr,nlp,language
Platform: UNKNOWN
Classifier: Programming Language :: Python :: 3
Classifier: Programming Language :: Python :: 3.6
Classifier: Programming Language :: Python :: 3.7
Classifier: Programming Language :: Python :: 3.8
Classifier: Programming Language :: Python :: 3.9
Classifier: Programming Language :: Python :: 3.10
Classifier: License :: OSI Approved :: MIT License
Classifier: Operating System :: OS Independent
Classifier: Development Status :: 4 - Beta
Classifier: Intended Audience :: Developers
Classifier: Intended Audience :: Education
Classifier: Intended Audience :: Science/Research
Classifier: Topic :: Text Processing :: Linguistic
Classifier: Topic :: Utilities
Requires-Python: >=3.6
License-File: LICENSE
Requires-Dist: pymupdf (>=1.18.0)
Requires-Dist: Pillow (>=8.0.0)
Requires-Dist: pytesseract (>=0.3.0)
Requires-Dist: deepl (>=1.17.0)
Requires-Dist: requests (>=2.25.0)
Requires-Dist: Werkzeug (>=2.0.0)
Requires-Dist: aiohttp (>=3.7.4)
